[
  {
    "nombre": "Jose Luis",
    "apellidos": "Garcia Mantero",
    "correo": "joselgarciamant1@gmail.com",
    "contrasenya": "mementoMori45",
    "direccion": "Calle España 19, Piso 2, 47630, Gandia, Valencia",
    "fecha-registro": "2023-02-10",
    "espacio-personal": {
      "notificaciones": [
        {
          "incidencia": "La iluminación del Huerto 1 está bajando más de lo normal",
          "fecha": "2023-05-03"
        },
        {
          "incidencia": "La temperatura del Huerto 2 ha bajado drásticamente",
          "fecha": "2023-05-01"
        }
      ],
      "huertos": [
        {
          "nombre": "Huerto 1",
          "localizacion": "39.033740,-0.203123",
          "hora": "19:25",
          "fecha": "2023-06-17",
          "parametros-tiempo-real": {
            "humedad": "98%",
            "salinidad": "12%",
            "iluminacion": "Alta",
            "pH": "7.4",
            "temperatura": "17ºC"
          },
          "parametros-historico": {
            "humedad": [{},{}],
            "salinidad": [{},{}],
            "iluminacion": [{},{}],
            "pH": [{},{}],
            "temperatura": [{},{}]
          }
        },
        {
          "nombre": "Huerto 2",
          "localizacion": "39.043740,-0.213123",
          "hora": "19:25",
          "fecha": "2023-06-17",
          "parametros-tiempo-real": {
            "humedad": "70%",
            "salinidad": "25%",
            "iluminacion": "Media",
            "pH": "8.12",
            "temperatura": "19ºC"
          },
          "parametros-historico": {
            "humedad": [{},{}],
            "salinidad": [{},{}],
            "iluminacion": [{},{}],
            "pH": [{},{}],
            "temperatura": [{},{}]
          }
        }
      ]
    }
  },

  {
    "nombre": "Marcos",
    "apellidos": "Ramos Edward",
    "correo": "marcramedwa@gmail.com",
    "contrasenya": "amuntValencia98",
    "direccion": "Calle Rafael Pino 96, Piso 1, 47630, Gandia, Valencia",
    "fecha-registro": "2023-02-26",
    "espacio-personal": {
      "notificaciones": [
        {
          "incidencia": "La humedad del Huerto 1 ha subido demasiado",
          "fecha": "2023-05-01"
        },
        {
          "incidencia": "El pH del Huerto 2 ha subido drásticamente",
          "fecha": "2023-05-02"
        }
      ],
      "huertos": [
        {
          "nombre": "Huerto 1",
          "localizacion": "39.033740,-0.203123",
          "hora": "19:25",
          "fecha": "2023-06-17",
          "parametros-tiempo-real": {
            "humedad": "90%",
            "salinidad": "5%",
            "iluminacion": "Alta",
            "pH": "6.2",
            "temperatura": "11ºC"
          },
          "parametros-historico": {
            "humedad": [{},{}],
            "salinidad": [{},{}],
            "iluminacion": [{},{}],
            "pH": [{},{}],
            "temperatura": [{},{}]
          }
        },
        {
          "nombre": "Huerto 2",
          "localizacion": "39.043740,-0.213123",
          "hora": "19:25",
          "fecha": "2023-06-17",
          "parametros-tiempo-real": {
            "humedad": "50%",
            "salinidad": "31%",
            "iluminacion": "Media",
            "pH": "7.1",
            "temperatura": "15ºC"
          },
          "parametros-historico": {
            "humedad": [{},{}],
            "salinidad": [{},{}],
            "iluminacion": [{},{}],
            "pH": [{},{}],
            "temperatura": [{},{}]
          }
        }
      ]
    }
  }
]